monaco_f1_report-0.1.1.dist-info/licenses/LICENSE
monaco_report/__init__.py
monaco_report/__main__.py
monaco_report/main.py
monaco_report/report.py
monaco_report/data/abbreviations.txt
monaco_report/data/end.log
monaco_report/data/start.log
monaco_f1_report-0.1.1.dist-info/METADATA
monaco_f1_report-0.1.1.dist-info/WHEEL
monaco_f1_report-0.1.1.dist-info/entry_points.txt
monaco_f1_report-0.1.1.dist-info/top_level.txt
monaco_f1_report-0.1.1.dist-info/RECORD
