Metadata-Version: 2.4
Name: monaco-f1-report
Version: 0.1.1
Summary: Formula 1 Monaco 2018 Qualification report generator
Author-email: Oleksii Ovcharuk <ovcharuk19951209@gmail.com>
License: MIT License
Classifier: Programming Language :: Python :: 3
Classifier: Programming Language :: Python :: 3 :: Only
Classifier: License :: OSI Approved :: MIT License
Classifier: Operating System :: OS Independent
Requires-Python: >=3.8
License-File: LICENSE
Dynamic: license-file
